utils.py
gpt_sovits_python/__init__.py
gpt_sovits_python/utils.py
gpt_sovits_python/AR/__init__.py
gpt_sovits_python/AR/data/__init__.py
gpt_sovits_python/AR/data/bucket_sampler.py
gpt_sovits_python/AR/data/data_module.py
gpt_sovits_python/AR/data/dataset.py
gpt_sovits_python/AR/models/__init__.py
gpt_sovits_python/AR/models/t2s_lightning_module.py
gpt_sovits_python/AR/models/t2s_lightning_module_onnx.py
gpt_sovits_python/AR/models/t2s_model.py
gpt_sovits_python/AR/models/t2s_model_batch_only.py
gpt_sovits_python/AR/models/t2s_model_onnx.py
gpt_sovits_python/AR/models/utils.py
gpt_sovits_python/AR/modules/__init__.py
gpt_sovits_python/AR/modules/activation.py
gpt_sovits_python/AR/modules/activation_onnx.py
gpt_sovits_python/AR/modules/embedding.py
gpt_sovits_python/AR/modules/embedding_onnx.py
gpt_sovits_python/AR/modules/lr_schedulers.py
gpt_sovits_python/AR/modules/optim.py
gpt_sovits_python/AR/modules/patched_mha_with_cache.py
gpt_sovits_python/AR/modules/patched_mha_with_cache_onnx.py
gpt_sovits_python/AR/modules/scaling.py
gpt_sovits_python/AR/modules/transformer.py
gpt_sovits_python/AR/modules/transformer_onnx.py
gpt_sovits_python/AR/text_processing/__init__.py
gpt_sovits_python/AR/text_processing/phonemizer.py
gpt_sovits_python/AR/text_processing/symbols.py
gpt_sovits_python/AR/utils/__init__.py
gpt_sovits_python/AR/utils/initialize.py
gpt_sovits_python/AR/utils/io.py
gpt_sovits_python/TTS_infer_pack/TTS.py
gpt_sovits_python/TTS_infer_pack/TextPreprocessor.py
gpt_sovits_python/TTS_infer_pack/__init__.py
gpt_sovits_python/TTS_infer_pack/setup_logger.py
gpt_sovits_python/TTS_infer_pack/text_segmentation_method.py
gpt_sovits_python/feature_extractor/__init__.py
gpt_sovits_python/feature_extractor/cnhubert.py
gpt_sovits_python/feature_extractor/whisper_enc.py
gpt_sovits_python/module/__init__.py
gpt_sovits_python/module/attentions.py
gpt_sovits_python/module/attentions_onnx.py
gpt_sovits_python/module/commons.py
gpt_sovits_python/module/core_vq.py
gpt_sovits_python-1.0.0.dist-info/LICENSE.txt
gpt_sovits_python-1.0.0.dist-info/METADATA
gpt_sovits_python-1.0.0.dist-info/WHEEL
gpt_sovits_python-1.0.0.dist-info/top_level.txt
gpt_sovits_python-1.0.0.dist-info/RECORD
