Metadata-Version: 2.1
Name: gpt_sovits_python
Version: 1.0.0
Summary: Python wrapper for fast inference with GPT-SoVITS
Home-page: https://github.com/R3gm/gpt_sovits_python
Author: R3gm
License: MIT
Requires-Python: >=3.10
License-File: LICENSE.txt
Requires-Dist: ffmpeg-python
Requires-Dist: pyopenjtalk
Requires-Dist: einops
Requires-Dist: LangSegment >=0.2.0
Requires-Dist: cn2an
Requires-Dist: pypinyin
Requires-Dist: jieba-fast
Requires-Dist: g2p-en
Requires-Dist: typing-extensions ==4.9.0
Requires-Dist: typeguard ==4.2.0
Requires-Dist: pytorch-lightning
Provides-Extra: all
Requires-Dist: torch ; extra == 'all'
Requires-Dist: numpy ; extra == 'all'
Requires-Dist: scipy ; extra == 'all'
Requires-Dist: tensorboard ; extra == 'all'
Requires-Dist: librosa ==0.9.2 ; extra == 'all'
Requires-Dist: numba ==0.56.4 ; extra == 'all'
Requires-Dist: ffmpeg-python ; extra == 'all'
Requires-Dist: onnxruntime ; extra == 'all'
Requires-Dist: tqdm ; extra == 'all'
Requires-Dist: funasr ==1.0.0 ; extra == 'all'
Requires-Dist: torchaudio ; extra == 'all'
Requires-Dist: modelscope ==1.10.0 ; extra == 'all'
Requires-Dist: sentencepiece ; extra == 'all'
Requires-Dist: transformers ; extra == 'all'
Requires-Dist: chardet ; extra == 'all'
Requires-Dist: PyYAML ; extra == 'all'
Requires-Dist: psutil ; extra == 'all'
Requires-Dist: jieba ; extra == 'all'
Requires-Dist: Faster-Whisper ; extra == 'all'
Requires-Dist: wordsegment ; extra == 'all'
